Metadata-Version: 1.0
Name: qalioss
Version: 0.0.2
Summary: self module for quickly uploading or downloading folders from ali oss
Home-page: UNKNOWN
Author: zwy
Author-email: zuowangyang@foxmail.com
License: MIT License
Keywords: alioss,aliyun
Platform: any
